{"results": [{"dataset": "aster30m", "elevation": 125.0, "location": {"lat": 42.3941, "lng": -72.5215}}, {"dataset": "aster30m", "elevation": 113.0, "location": {"lat": 42.39269, "lng": -72.52014}}, {"dataset": "aster30m", "elevation": 82.0, "location": {"lat": 42.40202, "lng": -72.52092}}, {"dataset": "aster30m", "elevation": 82.0, "location": {"lat": 42.40244, "lng": -72.521}}, {"dataset": "aster30m", "elevation": 63.0, "location": {"lat": 42.36374, "lng": -72.53472}}, {"dataset": "aster30m", "elevation": 65.0, "location": {"lat": 42.36374, "lng": -72.5336}}, {"dataset": "aster30m", "elevation": 70.0, "location": {"lat": 42.36559, "lng": -72.52813}}, {"dataset": "aster30m", "elevation": 74.0, "location": {"lat": 42.3661, "lng": -72.52816}}, {"dataset": "aster30m", "elevation": 50.0, "location": {"lat": 42.36874, "lng": -72.5336}}, {"dataset": "aster30m", "elevation": 46.0, "location": {"lat": 42.36881, "lng": -72.53466}}, {"dataset": "aster30m", "elevation": 55.0, "location": {"lat": 42.36958, "lng": -72.53335}}, {"dataset": "aster30m", "elevation": 53.0, "location": {"lat": 42.37384, "lng": -72.53142}}, {"dataset": "aster30m", "elevation": 51.0, "location": {"lat": 42.37369, "lng": -72.53193}}, {"dataset": "aster30m", "elevation": 51.0, "location": {"lat": 42.37239, "lng": -72.53194}}, {"dataset": "aster30m", "elevation": 50.0, "location": {"lat": 42.37175, "lng": -72.53308}}, {"dataset": "aster30m", "elevation": 51.0, "location": {"lat": 42.37354, "lng": -72.53332}}, {"dataset": "aster30m", "elevation": 51.0, "location": {"lat": 42.37356, "lng": -72.53312}}, {"dataset": "aster30m", "elevation": 50.0, "location": {"lat": 42.34092, "lng": -72.51997}}, {"dataset": "aster30m", "elevation": 51.0, "location": {"lat": 42.34091, "lng": -72.5198}}, {"dataset": "aster30m", "elevation": 51.0, "location": {"lat": 42.34051, "lng": -72.51987}}, {"dataset": "aster30m", "elevation": 51.0, "location": {"lat": 42.34053, "lng": -72.52005}}, {"dataset": "aster30m", "elevation": 51.0, "location": {"lat": 42.34047, "lng": -72.51971}}, {"dataset": "aster30m", "elevation": 52.0, "location": {"lat": 42.34003, "lng": -72.51981}}, {"dataset": "aster30m", "elevation": 54.0, "location": {"lat": 42.37237, "lng": -72.50132}}, {"dataset": "aster30m", "elevation": 55.0, "location": {"lat": 42.37239, "lng": -72.50163}}, {"dataset": "aster30m", "elevation": 57.0, "location": {"lat": 42.37275, "lng": -72.50239}}, {"dataset": "aster30m", "elevation": 57.0, "location": {"lat": 42.37293, "lng": -72.50239}}, {"dataset": "aster30m", "elevation": 80.0, "location": {"lat": 42.36353, "lng": -72.5071}}, {"dataset": "aster30m", "elevation": 72.0, "location": {"lat": 42.36387, "lng": -72.5067}}, {"dataset": "aster30m", "elevation": 75.0, "location": {"lat": 42.36791, "lng": -72.51115}}, {"dataset": "aster30m", "elevation": 77.0, "location": {"lat": 42.36766, "lng": -72.51106}}, {"dataset": "aster30m", "elevation": 78.0, "location": {"lat": 42.36693, "lng": -72.51192}}, {"dataset": "aster30m", "elevation": 80.0, "location": {"lat": 42.3665, "lng": -72.51217}}, {"dataset": "aster30m", "elevation": 84.0, "location": {"lat": 42.39077, "lng": -72.52356}}, {"dataset": "aster30m", "elevation": 82.0, "location": {"lat": 42.39073, "lng": -72.52406}}, {"dataset": "aster30m", "elevation": 75.0, "location": {"lat": 42.39498, "lng": -72.52681}}, {"dataset": "aster30m", "elevation": 76.0, "location": {"lat": 42.39511, "lng": -72.52724}}, {"dataset": "aster30m", "elevation": 76.0, "location": {"lat": 42.39517, "lng": -72.52729}}, {"dataset": "aster30m", "elevation": 72.0, "location": {"lat": 42.39527, "lng": -72.52657}}, {"dataset": "aster30m", "elevation": 73.0, "location": {"lat": 42.39533, "lng": -72.5266}}, {"dataset": "aster30m", "elevation": 76.0, "location": {"lat": 42.39549, "lng": -72.527}}, {"dataset": "aster30m", "elevation": 64.0, "location": {"lat": 42.40964, "lng": -72.53036}}, {"dataset": "aster30m", "elevation": 81.0, "location": {"lat": 42.36711, "lng": -72.5202}}, {"dataset": "aster30m", "elevation": 100.0, "location": {"lat": 42.3746, "lng": -72.51983}}, {"dataset": "aster30m", "elevation": 70.0, "location": {"lat": 42.39535, "lng": -72.52618}}, {"dataset": "aster30m", "elevation": 71.0, "location": {"lat": 42.3955, "lng": -72.5263}}, {"dataset": "aster30m", "elevation": 69.0, "location": {"lat": 42.39727, "lng": -72.52779}}, {"dataset": "aster30m", "elevation": 68.0, "location": {"lat": 42.38748, "lng": -72.52892}}, {"dataset": "aster30m", "elevation": 73.0, "location": {"lat": 42.38675, "lng": -72.52718}}, {"dataset": "aster30m", "elevation": 66.0, "location": {"lat": 42.34063, "lng": -72.49379}}, {"dataset": "aster30m", "elevation": 69.0, "location": {"lat": 42.33714, "lng": -72.49421}}, {"dataset": "aster30m", "elevation": 49.0, "location": {"lat": 42.34198, "lng": -72.49461}}, {"dataset": "aster30m", "elevation": 58.0, "location": {"lat": 42.33304, "lng": -72.4922}}, {"dataset": "aster30m", "elevation": 60.0, "location": {"lat": 42.33321, "lng": -72.49239}}, {"dataset": "aster30m", "elevation": 66.0, "location": {"lat": 42.34101, "lng": -72.49438}}, {"dataset": "aster30m", "elevation": 57.0, "location": {"lat": 42.33937, "lng": -72.49332}}, {"dataset": "aster30m", "elevation": 59.0, "location": {"lat": 42.33812, "lng": -72.49036}}, {"dataset": "aster30m", "elevation": 85.0, "location": {"lat": 42.32835, "lng": -72.49982}}, {"dataset": "aster30m", "elevation": 90.0, "location": {"lat": 42.32824, "lng": -72.50182}}, {"dataset": "aster30m", "elevation": 106.0, "location": {"lat": 42.32966, "lng": -72.5028}}, {"dataset": "aster30m", "elevation": 67.0, "location": {"lat": 42.32828, "lng": -72.50522}}, {"dataset": "aster30m", "elevation": 96.0, "location": {"lat": 42.34301, "lng": -72.4807}}, {"dataset": "aster30m", "elevation": 59.0, "location": {"lat": 42.39242, "lng": -72.53147}}, {"dataset": "aster30m", "elevation": 68.0, "location": {"lat": 42.39202, "lng": -72.53058}}, {"dataset": "aster30m", "elevation": 69.0, "location": {"lat": 42.39256, "lng": -72.5297}}, {"dataset": "aster30m", "elevation": 72.0, "location": {"lat": 42.39246, "lng": -72.52898}}, {"dataset": "aster30m", "elevation": 69.0, "location": {"lat": 42.39252, "lng": -72.53057}}, {"dataset": "aster30m", "elevation": 65.0, "location": {"lat": 42.39246, "lng": -72.53098}}, {"dataset": "aster30m", "elevation": 68.0, "location": {"lat": 42.39221, "lng": -72.53}}, {"dataset": "aster30m", "elevation": 70.0, "location": {"lat": 42.39179, "lng": -72.52994}}, {"dataset": "aster30m", "elevation": 69.0, "location": {"lat": 42.3915, "lng": -72.52986}}, {"dataset": "aster30m", "elevation": 70.0, "location": {"lat": 42.3916, "lng": -72.52936}}, {"dataset": "aster30m", "elevation": 69.0, "location": {"lat": 42.39146, "lng": -72.53007}}, {"dataset": "aster30m", "elevation": 66.0, "location": {"lat": 42.3912, "lng": -72.5311}}, {"dataset": "aster30m", "elevation": 67.0, "location": {"lat": 42.39116, "lng": -72.53125}}, {"dataset": "aster30m", "elevation": 56.0, "location": {"lat": 42.39036, "lng": -72.53274}}, {"dataset": "aster30m", "elevation": 77.0, "location": {"lat": 42.39391, "lng": -72.52633}}, {"dataset": "aster30m", "elevation": 71.0, "location": {"lat": 42.39186, "lng": -72.52555}}, {"dataset": "aster30m", "elevation": 72.0, "location": {"lat": 42.39185, "lng": -72.52547}}, {"dataset": "aster30m", "elevation": 78.0, "location": {"lat": 42.36315, "lng": -72.48377}}, {"dataset": "aster30m", "elevation": 95.0, "location": {"lat": 42.36629, "lng": -72.48126}}, {"dataset": "aster30m", "elevation": 76.0, "location": {"lat": 42.36829, "lng": -72.48172}}, {"dataset": "aster30m", "elevation": 79.0, "location": {"lat": 42.39369, "lng": -72.527}}, {"dataset": "aster30m", "elevation": 60.0, "location": {"lat": 42.39391, "lng": -72.53127}}, {"dataset": "aster30m", "elevation": 64.0, "location": {"lat": 42.39412, "lng": -72.53055}}, {"dataset": "aster30m", "elevation": 64.0, "location": {"lat": 42.39433, "lng": -72.53069}}, {"dataset": "aster30m", "elevation": 74.0, "location": {"lat": 42.39443, "lng": -72.52908}}, {"dataset": "aster30m", "elevation": 64.0, "location": {"lat": 42.39454, "lng": -72.53093}}, {"dataset": "aster30m", "elevation": 75.0, "location": {"lat": 42.39455, "lng": -72.52867}}, {"dataset": "aster30m", "elevation": 65.0, "location": {"lat": 42.39455, "lng": -72.5308}}, {"dataset": "aster30m", "elevation": 64.0, "location": {"lat": 42.39456, "lng": -72.53117}}, {"dataset": "aster30m", "elevation": 66.0, "location": {"lat": 42.39458, "lng": -72.53068}}, {"dataset": "aster30m", "elevation": 68.0, "location": {"lat": 42.39459, "lng": -72.53023}}, {"dataset": "aster30m", "elevation": 75.0, "location": {"lat": 42.39459, "lng": -72.52857}}, {"dataset": "aster30m", "elevation": 80.0, "location": {"lat": 42.39464, "lng": -72.52772}}, {"dataset": "aster30m", "elevation": 66.0, "location": {"lat": 42.39466, "lng": -72.53148}}, {"dataset": "aster30m", "elevation": 76.0, "location": {"lat": 42.39469, "lng": -72.5282}}, {"dataset": "aster30m", "elevation": 67.0, "location": {"lat": 42.3947, "lng": -72.53162}}, {"dataset": "aster30m", "elevation": 69.0, "location": {"lat": 42.39483, "lng": -72.53141}}, {"dataset": "aster30m", "elevation": 74.0, "location": {"lat": 42.39482, "lng": -72.52886}}], "status": "OK"}