{"results": [{"dataset": "aster30m", "elevation": 117.0, "location": {"lat": 42.39235, "lng": -72.51888}}, {"dataset": "aster30m", "elevation": 115.0, "location": {"lat": 42.39258, "lng": -72.51926}}, {"dataset": "aster30m", "elevation": 117.0, "location": {"lat": 42.39209, "lng": -72.51912}}, {"dataset": "aster30m", "elevation": 119.0, "location": {"lat": 42.39199, "lng": -72.51943}}, {"dataset": "aster30m", "elevation": 122.0, "location": {"lat": 42.39161, "lng": -72.51996}}, {"dataset": "aster30m", "elevation": 122.0, "location": {"lat": 42.39172, "lng": -72.51937}}, {"dataset": "aster30m", "elevation": 121.0, "location": {"lat": 42.39173, "lng": -72.51898}}, {"dataset": "aster30m", "elevation": 118.0, "location": {"lat": 42.39165, "lng": -72.51836}}, {"dataset": "aster30m", "elevation": 116.0, "location": {"lat": 42.39251, "lng": -72.51924}}, {"dataset": "aster30m", "elevation": 116.0, "location": {"lat": 42.39261, "lng": -72.51892}}, {"dataset": "aster30m", "elevation": 115.0, "location": {"lat": 42.39264, "lng": -72.51855}}, {"dataset": "aster30m", "elevation": 113.0, "location": {"lat": 42.3925, "lng": -72.51769}}, {"dataset": "aster30m", "elevation": 117.0, "location": {"lat": 42.39259, "lng": -72.51654}}, {"dataset": "aster30m", "elevation": 115.0, "location": {"lat": 42.39267, "lng": -72.51847}}, {"dataset": "aster30m", "elevation": 105.0, "location": {"lat": 42.38978, "lng": -72.51922}}, {"dataset": "aster30m", "elevation": 107.0, "location": {"lat": 42.38961, "lng": -72.51916}}, {"dataset": "aster30m", "elevation": 107.0, "location": {"lat": 42.38973, "lng": -72.51906}}, {"dataset": "aster30m", "elevation": 106.0, "location": {"lat": 42.38971, "lng": -72.51919}}, {"dataset": "aster30m", "elevation": 106.0, "location": {"lat": 42.38964, "lng": -72.51933}}, {"dataset": "aster30m", "elevation": 89.0, "location": {"lat": 42.38967, "lng": -72.52102}}, {"dataset": "aster30m", "elevation": 89.0, "location": {"lat": 42.38968, "lng": -72.52073}}, {"dataset": "aster30m", "elevation": 85.0, "location": {"lat": 42.3849, "lng": -72.52169}}, {"dataset": "aster30m", "elevation": 81.0, "location": {"lat": 42.3849, "lng": -72.52206}}, {"dataset": "aster30m", "elevation": 77.0, "location": {"lat": 42.39474, "lng": -72.52395}}, {"dataset": "aster30m", "elevation": 80.0, "location": {"lat": 42.39418, "lng": -72.52393}}, {"dataset": "aster30m", "elevation": 80.0, "location": {"lat": 42.39475, "lng": -72.52373}}, {"dataset": "aster30m", "elevation": 80.0, "location": {"lat": 42.39486, "lng": -72.52375}}, {"dataset": "aster30m", "elevation": 76.0, "location": {"lat": 42.3948, "lng": -72.52395}}, {"dataset": "aster30m", "elevation": 72.0, "location": {"lat": 42.39534, "lng": -72.52434}}, {"dataset": "aster30m", "elevation": 79.0, "location": {"lat": 42.39475, "lng": -72.52382}}, {"dataset": "aster30m", "elevation": 79.0, "location": {"lat": 42.39484, "lng": -72.52382}}, {"dataset": "aster30m", "elevation": 72.0, "location": {"lat": 42.39535, "lng": -72.52433}}, {"dataset": "aster30m", "elevation": 69.0, "location": {"lat": 42.39577, "lng": -72.52487}}, {"dataset": "aster30m", "elevation": 82.0, "location": {"lat": 42.32577, "lng": -72.53205}}, {"dataset": "aster30m", "elevation": 76.0, "location": {"lat": 42.32634, "lng": -72.53193}}, {"dataset": "aster30m", "elevation": 78.0, "location": {"lat": 42.32613, "lng": -72.53193}}, {"dataset": "aster30m", "elevation": 87.0, "location": {"lat": 42.3236, "lng": -72.52955}}, {"dataset": "aster30m", "elevation": 86.0, "location": {"lat": 42.3236, "lng": -72.52998}}, {"dataset": "aster30m", "elevation": 85.0, "location": {"lat": 42.32346, "lng": -72.52956}}, {"dataset": "aster30m", "elevation": 85.0, "location": {"lat": 42.32271, "lng": -72.53039}}, {"dataset": "aster30m", "elevation": 83.0, "location": {"lat": 42.32288, "lng": -72.53027}}, {"dataset": "aster30m", "elevation": 84.0, "location": {"lat": 42.32268, "lng": -72.53021}}, {"dataset": "aster30m", "elevation": 84.0, "location": {"lat": 42.32283, "lng": -72.53031}}, {"dataset": "aster30m", "elevation": 88.0, "location": {"lat": 42.32296, "lng": -72.53204}}, {"dataset": "aster30m", "elevation": 86.0, "location": {"lat": 42.32315, "lng": -72.53188}}, {"dataset": "aster30m", "elevation": 86.0, "location": {"lat": 42.32311, "lng": -72.53201}}, {"dataset": "aster30m", "elevation": 86.0, "location": {"lat": 42.32303, "lng": -72.53219}}, {"dataset": "aster30m", "elevation": 88.0, "location": {"lat": 42.32295, "lng": -72.5322}}, {"dataset": "aster30m", "elevation": 85.0, "location": {"lat": 42.32303, "lng": -72.5317}}, {"dataset": "aster30m", "elevation": 55.0, "location": {"lat": 42.36964, "lng": -72.50079}}, {"dataset": "aster30m", "elevation": 57.0, "location": {"lat": 42.36927, "lng": -72.49901}}, {"dataset": "aster30m", "elevation": 50.0, "location": {"lat": 42.40258, "lng": -72.53362}}, {"dataset": "aster30m", "elevation": 49.0, "location": {"lat": 42.40257, "lng": -72.53405}}, {"dataset": "aster30m", "elevation": 54.0, "location": {"lat": 42.40301, "lng": -72.5316}}, {"dataset": "aster30m", "elevation": 52.0, "location": {"lat": 42.40286, "lng": -72.53156}}, {"dataset": "aster30m", "elevation": 49.0, "location": {"lat": 42.40384, "lng": -72.5322}}, {"dataset": "aster30m", "elevation": 49.0, "location": {"lat": 42.404, "lng": -72.53223}}, {"dataset": "aster30m", "elevation": 48.0, "location": {"lat": 42.40368, "lng": -72.53386}}, {"dataset": "aster30m", "elevation": 49.0, "location": {"lat": 42.40379, "lng": -72.53388}}, {"dataset": "aster30m", "elevation": 50.0, "location": {"lat": 42.40228, "lng": -72.53547}}, {"dataset": "aster30m", "elevation": 56.0, "location": {"lat": 42.40292, "lng": -72.53025}}, {"dataset": "aster30m", "elevation": 57.0, "location": {"lat": 42.3704, "lng": -72.4991}}, {"dataset": "aster30m", "elevation": 58.0, "location": {"lat": 42.37073, "lng": -72.49907}}, {"dataset": "aster30m", "elevation": 58.0, "location": {"lat": 42.37089, "lng": -72.49896}}, {"dataset": "aster30m", "elevation": 62.0, "location": {"lat": 42.36872, "lng": -72.49753}}, {"dataset": "aster30m", "elevation": 59.0, "location": {"lat": 42.36954, "lng": -72.49811}}, {"dataset": "aster30m", "elevation": 57.0, "location": {"lat": 42.36405, "lng": -72.48757}}, {"dataset": "aster30m", "elevation": 60.0, "location": {"lat": 42.36437, "lng": -72.48726}}, {"dataset": "aster30m", "elevation": 61.0, "location": {"lat": 42.36433, "lng": -72.48704}}, {"dataset": "aster30m", "elevation": 102.0, "location": {"lat": 42.35126, "lng": -72.47715}}, {"dataset": "aster30m", "elevation": 49.0, "location": {"lat": 42.40474, "lng": -72.5356}}, {"dataset": "aster30m", "elevation": 48.0, "location": {"lat": 42.40482, "lng": -72.53477}}, {"dataset": "aster30m", "elevation": 49.0, "location": {"lat": 42.40505, "lng": -72.53579}}, {"dataset": "aster30m", "elevation": 46.0, "location": {"lat": 42.40521, "lng": -72.53428}}, {"dataset": "aster30m", "elevation": 46.0, "location": {"lat": 42.40529, "lng": -72.53393}}, {"dataset": "aster30m", "elevation": 46.0, "location": {"lat": 42.40588, "lng": -72.53398}}, {"dataset": "aster30m", "elevation": 46.0, "location": {"lat": 42.40499, "lng": -72.5335}}, {"dataset": "aster30m", "elevation": 47.0, "location": {"lat": 42.40509, "lng": -72.53245}}, {"dataset": "aster30m", "elevation": 47.0, "location": {"lat": 42.40538, "lng": -72.53388}}, {"dataset": "aster30m", "elevation": 49.0, "location": {"lat": 42.40542, "lng": -72.5335}}, {"dataset": "aster30m", "elevation": 51.0, "location": {"lat": 42.40561, "lng": -72.5324}}, {"dataset": "aster30m", "elevation": 48.0, "location": {"lat": 42.40441, "lng": -72.53241}}, {"dataset": "aster30m", "elevation": 44.0, "location": {"lat": 42.40472, "lng": -72.533}}, {"dataset": "aster30m", "elevation": 49.0, "location": {"lat": 42.40574, "lng": -72.53531}}, {"dataset": "aster30m", "elevation": 49.0, "location": {"lat": 42.40532, "lng": -72.53522}}, {"dataset": "aster30m", "elevation": 49.0, "location": {"lat": 42.40511, "lng": -72.53529}}, {"dataset": "aster30m", "elevation": 48.0, "location": {"lat": 42.40536, "lng": -72.53484}}, {"dataset": "aster30m", "elevation": 48.0, "location": {"lat": 42.40483, "lng": -72.53421}}, {"dataset": "aster30m", "elevation": 48.0, "location": {"lat": 42.40487, "lng": -72.5342}}, {"dataset": "aster30m", "elevation": 50.0, "location": {"lat": 42.40472, "lng": -72.53573}}, {"dataset": "aster30m", "elevation": 47.0, "location": {"lat": 42.40579, "lng": -72.53326}}, {"dataset": "aster30m", "elevation": 48.0, "location": {"lat": 42.40573, "lng": -72.53341}}, {"dataset": "aster30m", "elevation": 50.0, "location": {"lat": 42.40644, "lng": -72.53137}}, {"dataset": "aster30m", "elevation": 48.0, "location": {"lat": 42.4064, "lng": -72.53451}}, {"dataset": "aster30m", "elevation": 47.0, "location": {"lat": 42.40593, "lng": -72.53441}}, {"dataset": "aster30m", "elevation": 45.0, "location": {"lat": 42.40582, "lng": -72.53447}}, {"dataset": "aster30m", "elevation": 47.0, "location": {"lat": 42.40543, "lng": -72.53436}}, {"dataset": "aster30m", "elevation": 47.0, "location": {"lat": 42.406, "lng": -72.53378}}, {"dataset": "aster30m", "elevation": 48.0, "location": {"lat": 42.40646, "lng": -72.53386}}, {"dataset": "aster30m", "elevation": 51.0, "location": {"lat": 42.405, "lng": -72.53167}}], "status": "OK"}