{"results": [{"dataset": "aster30m", "elevation": 77.0, "location": {"lat": 42.39831, "lng": -72.52438}}, {"dataset": "aster30m", "elevation": 72.0, "location": {"lat": 42.39894, "lng": -72.52437}}, {"dataset": "aster30m", "elevation": 80.0, "location": {"lat": 42.39968, "lng": -72.52426}}, {"dataset": "aster30m", "elevation": 74.0, "location": {"lat": 42.39824, "lng": -72.52461}}, {"dataset": "aster30m", "elevation": 68.0, "location": {"lat": 42.39895, "lng": -72.5246}}, {"dataset": "aster30m", "elevation": 78.0, "location": {"lat": 42.39979, "lng": -72.52448}}, {"dataset": "aster30m", "elevation": 75.0, "location": {"lat": 42.39979, "lng": -72.52471}}, {"dataset": "aster30m", "elevation": 66.0, "location": {"lat": 42.39898, "lng": -72.52502}}, {"dataset": "aster30m", "elevation": 73.0, "location": {"lat": 42.39981, "lng": -72.52491}}, {"dataset": "aster30m", "elevation": 71.0, "location": {"lat": 42.39979, "lng": -72.52513}}, {"dataset": "aster30m", "elevation": 66.0, "location": {"lat": 42.39912, "lng": -72.52544}}, {"dataset": "aster30m", "elevation": 70.0, "location": {"lat": 42.39981, "lng": -72.52535}}, {"dataset": "aster30m", "elevation": 65.0, "location": {"lat": 42.39916, "lng": -72.52565}}, {"dataset": "aster30m", "elevation": 70.0, "location": {"lat": 42.3998, "lng": -72.52557}}, {"dataset": "aster30m", "elevation": 65.0, "location": {"lat": 42.39918, "lng": -72.52585}}, {"dataset": "aster30m", "elevation": 69.0, "location": {"lat": 42.39979, "lng": -72.52578}}, {"dataset": "aster30m", "elevation": 70.0, "location": {"lat": 42.39914, "lng": -72.52802}}, {"dataset": "aster30m", "elevation": 65.0, "location": {"lat": 42.39919, "lng": -72.52758}}, {"dataset": "aster30m", "elevation": 60.0, "location": {"lat": 42.35639, "lng": -72.48673}}, {"dataset": "aster30m", "elevation": 70.0, "location": {"lat": 42.35627, "lng": -72.48535}}, {"dataset": "aster30m", "elevation": 68.0, "location": {"lat": 42.35634, "lng": -72.48551}}, {"dataset": "aster30m", "elevation": 73.0, "location": {"lat": 42.35611, "lng": -72.48496}}, {"dataset": "aster30m", "elevation": 69.0, "location": {"lat": 42.3562, "lng": -72.48561}}, {"dataset": "aster30m", "elevation": 74.0, "location": {"lat": 42.35598, "lng": -72.48506}}, {"dataset": "aster30m", "elevation": 71.0, "location": {"lat": 42.356, "lng": -72.48575}}, {"dataset": "aster30m", "elevation": 76.0, "location": {"lat": 42.35578, "lng": -72.48522}}, {"dataset": "aster30m", "elevation": 68.0, "location": {"lat": 42.35629, "lng": -72.48554}}, {"dataset": "aster30m", "elevation": 71.0, "location": {"lat": 42.35599, "lng": -72.48576}}, {"dataset": "aster30m", "elevation": 59.0, "location": {"lat": 42.35836, "lng": -72.48828}}, {"dataset": "aster30m", "elevation": 61.0, "location": {"lat": 42.35837, "lng": -72.488}}, {"dataset": "aster30m", "elevation": 59.0, "location": {"lat": 42.3589, "lng": -72.48817}}, {"dataset": "aster30m", "elevation": 61.0, "location": {"lat": 42.35887, "lng": -72.48792}}, {"dataset": "aster30m", "elevation": 54.0, "location": {"lat": 42.36048, "lng": -72.48868}}, {"dataset": "aster30m", "elevation": 57.0, "location": {"lat": 42.36063, "lng": -72.48848}}, {"dataset": "aster30m", "elevation": 60.0, "location": {"lat": 42.36086, "lng": -72.48851}}, {"dataset": "aster30m", "elevation": 63.0, "location": {"lat": 42.36098, "lng": -72.48753}}, {"dataset": "aster30m", "elevation": 50.0, "location": {"lat": 42.40319, "lng": -72.53395}}, {"dataset": "aster30m", "elevation": 77.0, "location": {"lat": 42.3676, "lng": -72.51106}}, {"dataset": "aster30m", "elevation": 78.0, "location": {"lat": 42.36742, "lng": -72.51107}}, {"dataset": "aster30m", "elevation": 78.0, "location": {"lat": 42.36773, "lng": -72.51831}}, {"dataset": "aster30m", "elevation": 78.0, "location": {"lat": 42.36771, "lng": -72.51798}}, {"dataset": "aster30m", "elevation": 94.0, "location": {"lat": 42.37475, "lng": -72.51471}}, {"dataset": "aster30m", "elevation": 87.0, "location": {"lat": 42.37474, "lng": -72.5139}}, {"dataset": "aster30m", "elevation": 84.0, "location": {"lat": 42.37336, "lng": -72.51336}}, {"dataset": "aster30m", "elevation": 84.0, "location": {"lat": 42.3738, "lng": -72.5129}}, {"dataset": "aster30m", "elevation": 83.0, "location": {"lat": 42.37334, "lng": -72.51316}}, {"dataset": "aster30m", "elevation": 85.0, "location": {"lat": 42.37382, "lng": -72.51314}}, {"dataset": "aster30m", "elevation": 87.0, "location": {"lat": 42.37589, "lng": -72.51227}}, {"dataset": "aster30m", "elevation": 87.0, "location": {"lat": 42.37583, "lng": -72.51227}}, {"dataset": "aster30m", "elevation": 86.0, "location": {"lat": 42.37556, "lng": -72.51229}}, {"dataset": "aster30m", "elevation": 89.0, "location": {"lat": 42.37718, "lng": -72.51124}}, {"dataset": "aster30m", "elevation": 89.0, "location": {"lat": 42.37719, "lng": -72.51207}}, {"dataset": "aster30m", "elevation": 80.0, "location": {"lat": 42.37627, "lng": -72.51138}}, {"dataset": "aster30m", "elevation": 81.0, "location": {"lat": 42.37647, "lng": -72.51117}}, {"dataset": "aster30m", "elevation": 78.0, "location": {"lat": 42.3678, "lng": -72.51791}}, {"dataset": "aster30m", "elevation": 78.0, "location": {"lat": 42.36768, "lng": -72.51781}}, {"dataset": "aster30m", "elevation": 84.0, "location": {"lat": 42.36921, "lng": -72.51776}}, {"dataset": "aster30m", "elevation": 80.0, "location": {"lat": 42.36902, "lng": -72.51773}}, {"dataset": "aster30m", "elevation": 81.0, "location": {"lat": 42.36885, "lng": -72.51791}}, {"dataset": "aster30m", "elevation": 82.0, "location": {"lat": 42.36862, "lng": -72.51798}}, {"dataset": "aster30m", "elevation": 81.0, "location": {"lat": 42.36859, "lng": -72.51779}}, {"dataset": "aster30m", "elevation": 78.0, "location": {"lat": 42.36882, "lng": -72.51771}}, {"dataset": "aster30m", "elevation": 89.0, "location": {"lat": 42.36952, "lng": -72.51864}}, {"dataset": "aster30m", "elevation": 92.0, "location": {"lat": 42.36967, "lng": -72.51771}}, {"dataset": "aster30m", "elevation": 90.0, "location": {"lat": 42.3697, "lng": -72.51661}}, {"dataset": "aster30m", "elevation": 90.0, "location": {"lat": 42.36966, "lng": -72.51688}}, {"dataset": "aster30m", "elevation": 78.0, "location": {"lat": 42.36926, "lng": -72.51613}}, {"dataset": "aster30m", "elevation": 75.0, "location": {"lat": 42.36899, "lng": -72.51533}}, {"dataset": "aster30m", "elevation": 74.0, "location": {"lat": 42.36893, "lng": -72.51562}}, {"dataset": "aster30m", "elevation": 73.0, "location": {"lat": 42.3689, "lng": -72.51554}}, {"dataset": "aster30m", "elevation": 72.0, "location": {"lat": 42.36879, "lng": -72.51593}}, {"dataset": "aster30m", "elevation": 74.0, "location": {"lat": 42.36895, "lng": -72.51534}}, {"dataset": "aster30m", "elevation": 77.0, "location": {"lat": 42.36909, "lng": -72.51531}}, {"dataset": "aster30m", "elevation": 83.0, "location": {"lat": 42.36984, "lng": -72.5143}}, {"dataset": "aster30m", "elevation": 82.0, "location": {"lat": 42.3698, "lng": -72.51426}}, {"dataset": "aster30m", "elevation": 83.0, "location": {"lat": 42.36955, "lng": -72.51474}}, {"dataset": "aster30m", "elevation": 79.0, "location": {"lat": 42.36949, "lng": -72.51433}}, {"dataset": "aster30m", "elevation": 81.0, "location": {"lat": 42.36926, "lng": -72.51505}}, {"dataset": "aster30m", "elevation": 80.0, "location": {"lat": 42.36925, "lng": -72.51557}}, {"dataset": "aster30m", "elevation": 76.0, "location": {"lat": 42.36908, "lng": -72.51557}}, {"dataset": "aster30m", "elevation": 86.0, "location": {"lat": 42.3695, "lng": -72.51558}}, {"dataset": "aster30m", "elevation": 80.0, "location": {"lat": 42.36914, "lng": -72.51755}}, {"dataset": "aster30m", "elevation": 83.0, "location": {"lat": 42.36922, "lng": -72.51761}}, {"dataset": "aster30m", "elevation": 82.0, "location": {"lat": 42.3694, "lng": -72.51574}}, {"dataset": "aster30m", "elevation": 83.0, "location": {"lat": 42.36939, "lng": -72.51557}}, {"dataset": "aster30m", "elevation": 85.0, "location": {"lat": 42.3695, "lng": -72.51505}}, {"dataset": "aster30m", "elevation": 72.0, "location": {"lat": 42.36886, "lng": -72.51513}}, {"dataset": "aster30m", "elevation": 74.0, "location": {"lat": 42.36899, "lng": -72.51505}}, {"dataset": "aster30m", "elevation": 77.0, "location": {"lat": 42.36909, "lng": -72.51517}}, {"dataset": "aster30m", "elevation": 76.0, "location": {"lat": 42.36912, "lng": -72.51462}}, {"dataset": "aster30m", "elevation": 79.0, "location": {"lat": 42.36918, "lng": -72.51487}}, {"dataset": "aster30m", "elevation": 74.0, "location": {"lat": 42.36904, "lng": -72.51472}}, {"dataset": "aster30m", "elevation": 73.0, "location": {"lat": 42.36906, "lng": -72.5143}}, {"dataset": "aster30m", "elevation": 70.0, "location": {"lat": 42.36899, "lng": -72.51405}}, {"dataset": "aster30m", "elevation": 73.0, "location": {"lat": 42.36932, "lng": -72.51357}}, {"dataset": "aster30m", "elevation": 78.0, "location": {"lat": 42.36981, "lng": -72.51345}}, {"dataset": "aster30m", "elevation": 80.0, "location": {"lat": 42.37003, "lng": -72.51353}}, {"dataset": "aster30m", "elevation": 79.0, "location": {"lat": 42.36986, "lng": -72.51377}}, {"dataset": "aster30m", "elevation": 77.0, "location": {"lat": 42.36967, "lng": -72.51346}}, {"dataset": "aster30m", "elevation": 75.0, "location": {"lat": 42.36942, "lng": -72.51352}}], "status": "OK"}